{"name":"Perspectivedemo","tagline":"Simple demo  demostrating a perspective grid for use in digital painting","body":"# PerspectiveDemo\r\nThis is a simple javascript demo demonstrating how a perspective grid should be \r\nlaid out on a drawing/painting application. Drag the black circles around and it \r\nwill set up perspective lines according to how the perspective should be laid \r\nout along the represented surface, as well as showing the vanishing points.\r\n","google":"","note":"Don't delete this file! It's used internally to help with page regeneration."}